mergait/__init__.py
mergait/bouts.py
mergait/complexity.py
mergait/economy.py
mergait/filters.py
mergait/imu.py
mergait/music.py
mergait/music_library.py
mergait/obfuscate.py
mergait/rawreader.py
mergait/recipes.py
mergait/stats.py
mergait/symmetry.py
mergait/utility.py
mergait-0.0.8.dist-info/LICENSE
mergait-0.0.8.dist-info/METADATA
mergait-0.0.8.dist-info/WHEEL
mergait-0.0.8.dist-info/top_level.txt
mergait-0.0.8.dist-info/RECORD
