Metadata-Version: 2.1
Name: mergait
Version: 0.0.8
Summary: Read and process running gait related dataframes, ranging from raw (iPhone) activity and IMU data to footpod per-step data and music parameters.
Home-page: https://github.com/olafjanssen/mergait
Author: Olaf T.A. Janssen
Author-email: olaf.janssen@fontys.nl
License: MIT
Keywords: running,gait,mergait,imu,symmetry,accelerometer,footpods,spotify
Platform: UNKNOWN
Classifier: Programming Language :: Python :: 3.6
Classifier: License :: OSI Approved :: MIT License
Classifier: Operating System :: OS Independent
Requires-Python: >=3.6
License-File: LICENSE
Requires-Dist: pandas (>=1.2.3)
Requires-Dist: numpy (>=1.20.0)
Requires-Dist: spotipy (>=2.17.1)
Requires-Dist: scipy (>=1.6.2)
Requires-Dist: sklearn
Requires-Dist: neurokit2
